projectrexa/__init__.py
projectrexa/projectrexa.py
projectrexa-0.1.1.0.dist-info/METADATA
projectrexa-0.1.1.0.dist-info/WHEEL
projectrexa-0.1.1.0.dist-info/top_level.txt
projectrexa-0.1.1.0.dist-info/RECORD
