Metadata-Version: 2.1
Name: projectrexa
Version: 0.1.1.0
Summary: ProjectRexa SSO Managing Module
Home-page: https://github.com/Om-Mishra7/ProjectRexa-PyPI
Author: ProjectRexa
Author-email: admin@projectrexa.ml
License: UNKNOWN
Download-URL: https://github.com/Om-Mishra7/ProjectRexa-PyPI/archive/0.1.1.0.tar.gz
Platform: UNKNOWN
Classifier: Programming Language :: Python :: 3
Classifier: License :: OSI Approved :: MIT License
Classifier: Operating System :: OS Independent
Requires-Python: >=3
Requires-Dist: flask
Requires-Dist: cryptography
Requires-Dist: requests
